{
  "project_info": {
    "project_number": "285114139955",
    "project_id": "linkedin-a2769",
    "storage_bucket": "linkedin-a2769.firebasestorage.app"
  },
  "client": [
    {
      "client_info": {
        "mobilesdk_app_id": "1:285114139955:android:6fb78c18a218f4fb49aa46",
        "android_client_info": {
          "package_name": "com.example.linkedin"
        }
      },
      "oauth_client": [],
      "api_key": [
        {
          "current_key": "AIzaSyAIwgPe0EnYCIUhTlyJME-iipM4lglCNJk"
        }
      ],
      "services": {
        "appinvite_service": {
          "other_platform_oauth_client": []
        }
      }
    }
  ],
  "configuration_version": "1"
}